MANIFEST.in
README.txt
setup.cfg
setup.py
docs/HISTORY.txt
docs/LICENSE.GPL
docs/LICENSE.txt
docs/MANUAL.txt
raptus/__init__.py
raptus.article.contentswitcher.egg-info/PKG-INFO
raptus.article.contentswitcher.egg-info/SOURCES.txt
raptus.article.contentswitcher.egg-info/dependency_links.txt
raptus.article.contentswitcher.egg-info/entry_points.txt
raptus.article.contentswitcher.egg-info/namespace_packages.txt
raptus.article.contentswitcher.egg-info/not-zip-safe
raptus.article.contentswitcher.egg-info/requires.txt
raptus.article.contentswitcher.egg-info/top_level.txt
raptus/article/__init__.py
raptus/article/contentswitcher/__init__.py
raptus/article/contentswitcher/configure.zcml
raptus/article/contentswitcher/browser/__init__.py
raptus/article/contentswitcher/browser/configure.zcml
raptus/article/contentswitcher/browser/contentswitcher.gif
raptus/article/contentswitcher/browser/contentswitcher.init.js
raptus/article/contentswitcher/browser/contentswitcher.pt
raptus/article/contentswitcher/browser/contentswitcher.py
raptus/article/contentswitcher/browser/contentswitcher_teaser.gif
raptus/article/contentswitcher/i18n/raptus.article-de.mo
raptus/article/contentswitcher/i18n/raptus.article-de.po
raptus/article/contentswitcher/i18n/raptus.article.pot
raptus/article/contentswitcher/profiles/default/cssregistry.xml
raptus/article/contentswitcher/profiles/default/jsregistry.xml
raptus/article/contentswitcher/profiles/default/metadata.xml
raptus/article/contentswitcher/profiles/default/propertiestool.xml
raptus/article/contentswitcher/profiles/default/skins.xml
raptus/article/contentswitcher/profiles/default/viewlets.xml
raptus/article/contentswitcher/skins/raptus_article_contentswitcher/raptus.article.contentswitcher.css.dtml