Metadata-Version: 1.0
Name: raptus.article.contentswitcher
Version: 1.0b5
Summary: Provides a jQuery based content switcher
Home-page: http://raptus.com
Author: Raptus AG
Author-email: dev@raptus.com
License: GPL
Platform: UNKNOWN
Classifier: Programming Language :: Python
Classifier: Topic :: Software Development :: Libraries :: Python Modules
